{
    "titulo": "La ultima batalla",
    "imagen": "https:\/\/image.tmdb.org\/t\/p\/w342\/mwRZ00JgrpF2xTmO6cvl3eYu5X.jpg",
    "etiquetas": "Acción",
    "year": "2025",
    "created_at": "2025-05-26",
    "updated_at": "2026-01-30T08:11:15.000Z",
    "id_tmdb": "1465038",
    "type": "movie",
    "calidad": "HD",
    "synopsis": "Los asesinos más letales del mundo luchan a muerte en un torneo clandestino. Pero un grupo rebelde se infiltra con una misión: sobrevivir a la masacre...",
    "enlaces": [
        {
            "nombre": "Server 1",
            "url": "https:\/\/goodstream.one\/embed-266ycp4wg1m7.html",
            "type": "embed",
            "language": "Latino"
        }
    ]
}