{
    "id": "1782858693",
    "tmdb_id": "1165642",
    "titulo": "Lo que le falta a esta estrella",
    "original_name": "이 별에 필요한",
    "imagen": "\/6AmW8DglQ5VnOfW1lSMSOyfcwmW.jpg",
    "backdrop_path": "\/drSJ0HVuSNFMPq5VzAEHk37BiEC.jpg",
    "type": "movie",
    "year": "2025",
    "etiquetas": [
        "Animación",
        "Romance",
        "Ciencia ficción",
        "Drama"
    ],
    "calidad": [
        "720p"
    ],
    "rate": 7.29999999999999982236431605997495353221893310546875,
    "sinopsis": "La inmensidad del espacio infinito separa a dos amantes cuando una astronauta abandona la Tierra rumbo a Marte en este romance de animación que recorre todo el cosmos.",
    "cast": [
        {
            "name": "김태리",
            "character": "Nan-young (voice)",
            "profile_path": "\/gFofVUeVlIvBJMUv7maHQwWdfsk.jpg"
        },
        {
            "name": "홍경",
            "character": "Je-i (voice)",
            "profile_path": "\/wRXum47BB0ciPGINjCvT36rDuQE.jpg"
        },
        {
            "name": "권영미",
            "character": "Rosa (voice)",
            "profile_path": ""
        },
        {
            "name": "강구한",
            "character": "Yun-jae (voice)",
            "profile_path": "\/31Qme50mO7AZ0xUFWvO8qVbE6uJ.jpg"
        },
        {
            "name": "안영미",
            "character": "Ji-young (voice)",
            "profile_path": "\/354Kc5AjEvgXnWrQIXB9N0XlzeU.jpg"
        },
        {
            "name": "장미",
            "character": "Young Na-young \/ Detector (voice)",
            "profile_path": "\/1BQhoNpA5RTzaS7D2uyFzfAn12P.jpg"
        },
        {
            "name": "윤아영",
            "character": "Dia (voice)",
            "profile_path": "\/zdGLBgdLl2eHtK8xsZVGzJxvuoc.jpg"
        },
        {
            "name": "최한",
            "character": "Manager (voice)",
            "profile_path": "\/8ZRMUf6tSU0M24f3FBiFVGbBqXK.jpg"
        },
        {
            "name": "David J Robbins",
            "character": "Eugene \/ Jared (voice)",
            "profile_path": ""
        },
        {
            "name": "이명희",
            "character": "Director \/ Caregiver (voice)",
            "profile_path": "\/m8lEmbbCxpQLiUiPLd1euYXo7Ya.jpg"
        },
        {
            "name": "김진수",
            "character": "Reporter (voice)",
            "profile_path": ""
        },
        {
            "name": "박성영",
            "character": "Researcher (voice)",
            "profile_path": "\/kDMg6GRyR4Ud9nD0Ncnxi3AqQAD.jpg"
        },
        {
            "name": "오주희",
            "character": "Doctor (voice)",
            "profile_path": "\/bCU5oRd0wNAQMq2RgT5uczvvfIU.jpg"
        },
        {
            "name": "이보용",
            "character": "News Anchor (voice)",
            "profile_path": "\/pK2ARMLNV7EMftmveZTs9C4xkaQ.jpg"
        },
        {
            "name": "소새롬",
            "character": "Nancy \/ Linda (voice)",
            "profile_path": ""
        }
    ],
    "first_air_date": null,
    "last_air_date": null,
    "status": "Released",
    "runtime": 96,
    "enlaces": [
        {
            "nombre": "Ver 1",
            "url": "https:\/\/goodstream.one\/embed-qlfcslsho8f2.html",
            "type": "streaming",
            "language": "Latino",
            "quality": "720p"
        },
        {
            "nombre": "Descargar 1",
            "url": "https:\/\/goodstream.one\/qlfcslsho8f2",
            "type": "descarga",
            "language": "Latino",
            "quality": "720p"
        }
    ],
    "added_date": "2026-06-30 18:31:33",
    "created_at": "2026-06-30 18:31:33",
    "updated_at": "2026-06-30 18:32:27"
}